invokelint/__init__.py
invokelint/_clean.py
invokelint/dist.py
invokelint/lint.py
invokelint/py.typed
invokelint/ruff.py
invokelint/run.py
invokelint/style.py
invokelint/test.py
invokelint/path/__init__.py
invokelint-0.16.0.dist-info/licenses/LICENSE
invokelint-0.16.0.dist-info/METADATA
invokelint-0.16.0.dist-info/WHEEL
invokelint-0.16.0.dist-info/top_level.txt
invokelint-0.16.0.dist-info/RECORD
